package_src/__init__.py
package_src/main.py
newsboat_subscribe-1.0.2.dist-info/LICENSE
newsboat_subscribe-1.0.2.dist-info/METADATA
newsboat_subscribe-1.0.2.dist-info/WHEEL
newsboat_subscribe-1.0.2.dist-info/entry_points.txt
newsboat_subscribe-1.0.2.dist-info/top_level.txt
newsboat_subscribe-1.0.2.dist-info/RECORD
